{"asOf":"2026-05-20T04:07:29Z","regions":{"US":{"name":"United States","flag":"US"},"EU":{"name":"Euro Area","flag":"EU"},"CN":{"name":"China","flag":"CN"},"EM":{"name":"Emerging Mkts","flag":"EM"},"GL":{"name":"Global","flag":"GL"}},"healthScore":{"composite":58,"trend":0,"components":{"growth":71.0,"inflation":30.3,"labor":55.0,"monetary":63.5,"stress":69.1},"regimeLabel":"LATE-CYCLE EXPANSION","regimeColor":"amber"},"ticker":[{"sym":"SPX","val":"7,353.61","chg":"-0.67%","dir":"down"},{"sym":"DJI","val":"49,363.88","chg":"-0.65%","dir":"down"},{"sym":"NDX","val":"25,870.71","chg":"-0.84%","dir":"down"},{"sym":"VIX","val":"17.820","chg":"-3.31%","dir":"down"},{"sym":"WTI","val":"101.56","chg":"+2.72%","dir":"up"},{"sym":"BRENT","val":"106.11","chg":"+2.54%","dir":"up"},{"sym":"DXY","val":"119.28","chg":"+0.52%","dir":"up"},{"sym":"US10Y","val":"4.610","chg":"+0.44%","dir":"up"},{"sym":"2s10s","val":"0.5400","chg":"+0.00%","dir":"up"}]}